datark_py_mcp_server/__init__.py
datark_py_mcp_server-0.1.0.dist-info/METADATA
datark_py_mcp_server-0.1.0.dist-info/WHEEL
datark_py_mcp_server-0.1.0.dist-info/entry_points.txt
datark_py_mcp_server-0.1.0.dist-info/RECORD
