Metadata-Version: 2.4
Name: datark-py-mcp-server
Version: 0.1.0
Summary: Add your description here
Author-email: zhourui <zhourui@servyou.com.cn>
Requires-Python: >=3.13
Requires-Dist: mcp>=1.9.4
